smart_schema/__init__.py
smart_schema/__main__.py
smart_schema/adapters/csv_adapter.py
smart_schema/adapters/csv_inference.py
smart_schema/adapters/csv_splitter.py
smart_schema/adapters/csv_validation.py
smart_schema/cli/cli.py
smart_schema/cli/commands.py
smart_schema/core/__init__.py
smart_schema/core/model_generator.py
smart_schema/core/model_utils.py
smart_schema/core/model_validator.py
smart_schema/core/schema_inferrer.py
smart_schema/utils/data_transformer.py
smart_schema/utils/dataframe_utils.py
smart_schema-1.0.3.dist-info/METADATA
smart_schema-1.0.3.dist-info/WHEEL
smart_schema-1.0.3.dist-info/entry_points.txt
smart_schema-1.0.3.dist-info/licenses/LICENSE
smart_schema-1.0.3.dist-info/RECORD
