Metadata-Version: 2.4
Name: smart-schema
Version: 1.0.3
Summary: A tool for generating and validating data schemas
Project-URL: Homepage, https://github.com/ipriyaaanshu/smart-schema
Project-URL: Repository, https://github.com/ipriyaaanshu/smart-schema.git
Author-email: Priyanshu Sharma <ipriyaaanshu@gmail.com>
License: MIT
License-File: LICENSE
Classifier: Development Status :: 4 - Beta
Classifier: Intended Audience :: Developers
Classifier: License :: OSI Approved :: MIT License
Classifier: Programming Language :: Python :: 3
Classifier: Programming Language :: Python :: 3.8
Classifier: Programming Language :: Python :: 3.9
Classifier: Programming Language :: Python :: 3.10
Classifier: Programming Language :: Python :: 3.11
Requires-Python: >=3.9
Requires-Dist: click==8.1.7
Requires-Dist: openai>=1.82.0
Requires-Dist: pandas>=2.0.0
Requires-Dist: pyarrow>=20.0.0
Requires-Dist: pydantic>=2.0.0
Requires-Dist: rich==13.7.0
Requires-Dist: typer==0.12.3
